[{"Country":"United States","GDP Growth Weighted":1579960000000000.0,"GDP Military Weighted":367.8879973,"Int. Cap Weighted":26955900000000.0,"Income Weighted":3850.894513,"Trade Weighted":-52779300000000.0,"Unemployment Weighted":576.417684,"CPI Weighted":9794.538467,"Dollar Weighted":38413200000000.0,"GDP Debt Weighted":8064.882709,"Economic Indicator":317251000000000.0,"Rank":1,"Scaled Economic Indicator":80.0,"Log_Economic_Indicator":33.39071459},{"Country":"China","GDP Growth Weighted":805032000000000.0,"GDP Military Weighted":166.1666805,"Int. Cap Weighted":8735720000000.0,"Income Weighted":3857.657207,"Trade Weighted":19857700000000.0,"Unemployment Weighted":425.3374739,"CPI Weighted":10104.93944,"Dollar Weighted":252199000000000.0,"GDP Debt Weighted":3699.744247,"Economic Indicator":189086000000000.0,"Rank":2,"Scaled Economic Indicator":77.0951051,"Log_Economic_Indicator":32.8732211},{"Country":"Japan","GDP Growth Weighted":480654000000000.0,"GDP Military Weighted":89.32890375,"Int. Cap Weighted":11779800000000.0,"Income Weighted":2952.57127,"Trade Weighted":-135363000000.0,"Unemployment Weighted":356.5937132,"CPI Weighted":9640.711677,"Dollar Weighted":106039000000000.0,"GDP Debt Weighted":16140.90534,"Economic Indicator":107899000000000.0,"Rank":3,"Scaled Economic Indicator":73.94596978,"Log_Economic_Indicator":32.31221731},{"Country":"Eritrea","GDP Growth Weighted":389170000000000.0,"GDP Military Weighted":311.7795292,"Int. Cap Weighted":30841800000000.0,"Income Weighted":3439.017725,"Trade Weighted":936086000000.0,"Unemployment Weighted":544.3068052,"CPI Weighted":11083.11987,"Dollar Weighted":3653600000000.0,"GDP Debt Weighted":7805.504202,"Economic Indicator":81377100000000.0,"Rank":4,"Scaled Economic Indicator":72.36242121,"Log_Economic_Indicator":32.0301155},{"Country":"Germany","GDP Growth Weighted":326917000000000.0,"GDP Military Weighted":115.0598165,"Int. Cap Weighted":11314100000000.0,"Income Weighted":2930.674949,"Trade Weighted":19357000000000.0,"Unemployment Weighted":561.9074707,"CPI Weighted":9718.234545,"Dollar Weighted":17339100000000.0,"GDP Debt Weighted":4673.393457,"Economic Indicator":70184400000000.0,"Rank":5,"Scaled Economic Indicator":71.53181557,"Log_Economic_Indicator":31.88214698},{"Country":"United Kingdom","GDP Growth Weighted":251590000000000.0,"GDP Military Weighted":213.4397733,"Int. Cap Weighted":6076180000000.0,"Income Weighted":3186.66255,"Trade Weighted":-3511830000000.0,"Unemployment Weighted":534.9438212,"CPI Weighted":9892.6256,"Dollar Weighted":10999500000000.0,"GDP Debt Weighted":12909.91357,"Economic Indicator":51674300000000.0,"Rank":6,"Scaled Economic Indicator":69.81319084,"Log_Economic_Indicator":31.57598199},{"Country":"France","GDP Growth Weighted":240652000000000.0,"GDP Military Weighted":182.3975242,"Int. Cap Weighted":7413730000000.0,"Income Weighted":3023.286653,"Trade Weighted":-2107100000000.0,"Unemployment Weighted":869.7051943,"CPI Weighted":9611.877801,"Dollar Weighted":13518600000000.0,"GDP Debt Weighted":8289.467178,"Economic Indicator":50013000000000.0,"Rank":7,"Scaled Economic Indicator":69.62975223,"Log_Economic_Indicator":31.54330325},{"Country":"Italy","GDP Growth Weighted":187807000000000.0,"GDP Military Weighted":137.2996616,"Int. Cap Weighted":2735480000000.0,"Income Weighted":3290.48842,"Trade Weighted":2594070000000.0,"Unemployment Weighted":924.0121119,"CPI Weighted":9644.157833,"Dollar Weighted":12778700000000.0,"GDP Debt Weighted":12358.9257,"Economic Indicator":39372200000000.0,"Rank":8,"Scaled Economic Indicator":68.28691112,"Log_Economic_Indicator":31.30408237},{"Country":"India","GDP Growth Weighted":173138000000000.0,"GDP Military Weighted":250.2768317,"Int. Cap Weighted":927861000000.0,"Income Weighted":3217.691062,"Trade Weighted":-5613330000000.0,"Unemployment Weighted":753.5080129,"CPI Weighted":11486.09648,"Dollar Weighted":29723400000000.0,"GDP Debt Weighted":5024.054705,"Economic Indicator":37131300000000.0,"Rank":9,"Scaled Economic Indicator":67.95796155,"Log_Economic_Indicator":31.24548153},{"Country":"Brazil","GDP Growth Weighted":168166000000000.0,"GDP Military Weighted":135.6799548,"Int. Cap Weighted":1110060000000.0,"Income Weighted":4943.158784,"Trade Weighted":-840027000000.0,"Unemployment Weighted":931.8922873,"CPI Weighted":11319.35647,"Dollar Weighted":26662500000000.0,"GDP Debt Weighted":6727.662353,"Economic Indicator":36326400000000.0,"Rank":10,"Scaled Economic Indicator":67.83493502,"Log_Economic_Indicator":31.22356493},{"Country":"Russian Federation","GDP Growth Weighted":139669000000000.0,"GDP Military Weighted":366.8856478,"Int. Cap Weighted":3418960000000.0,"Income Weighted":3636.197178,"Trade Weighted":10429100000000.0,"Unemployment Weighted":585.5804324,"CPI Weighted":11435.84441,"Dollar Weighted":38479100000000.0,"GDP Debt Weighted":1398.596738,"Economic Indicator":33166600000000.0,"Rank":11,"Scaled Economic Indicator":67.32411235,"Log_Economic_Indicator":31.13256425},{"Country":"Canada","GDP Growth Weighted":145312000000000.0,"GDP Military Weighted":113.0274812,"Int. Cap Weighted":5468300000000.0,"Income Weighted":3164.042017,"Trade Weighted":-1213040000000.0,"Unemployment Weighted":673.3022069,"CPI Weighted":9803.724984,"Dollar Weighted":6188690000000.0,"GDP Debt Weighted":4891.516484,"Economic Indicator":30106800000000.0,"Rank":12,"Scaled Economic Indicator":66.7807714,"Log_Economic_Indicator":31.03577059},{"Country":"South Korea","GDP Growth Weighted":122127000000000.0,"GDP Military Weighted":236.9619363,"Int. Cap Weighted":2377980000000.0,"Income Weighted":3080.402183,"Trade Weighted":4553360000000.0,"Unemployment Weighted":321.1852542,"CPI Weighted":9682.530662,"Dollar Weighted":29714000000000.0,"GDP Debt Weighted":5560.70359,"Economic Indicator":28089900000000.0,"Rank":13,"Scaled Economic Indicator":66.39154684,"Log_Economic_Indicator":30.96643205},{"Country":"Spain","GDP Growth Weighted":122239000000000.0,"GDP Military Weighted":125.396603,"Int. Cap Weighted":4533200000000.0,"Income Weighted":3308.143559,"Trade Weighted":772884000000.0,"Unemployment Weighted":1638.487235,"CPI Weighted":9582.754244,"Dollar Weighted":4585440000000.0,"GDP Debt Weighted":7892.658367,"Economic Indicator":25436900000000.0,"Rank":14,"Scaled Economic Indicator":65.83464446,"Log_Economic_Indicator":30.86722248},{"Country":"Mexico","GDP Growth Weighted":106872000000000.0,"GDP Military Weighted":44.81675686,"Int. Cap Weighted":832772000000.0,"Income Weighted":3956.871159,"Trade Weighted":-1402230000000.0,"Unemployment Weighted":391.8831527,"CPI Weighted":10316.19826,"Dollar Weighted":13473800000000.0,"GDP Debt Weighted":5022.498231,"Economic Indicator":22664800000000.0,"Rank":15,"Scaled Economic Indicator":65.18692899,"Log_Economic_Indicator":30.75183499},{"Country":"Netherlands","GDP Growth Weighted":77027300000000.0,"GDP Military Weighted":121.4398877,"Int. Cap Weighted":18274900000000.0,"Income Weighted":2769.480058,"Trade Weighted":7079490000000.0,"Unemployment Weighted":470.6039068,"CPI Weighted":9810.758609,"Dollar Weighted":3637280000000.0,"GDP Debt Weighted":5871.32526,"Economic Indicator":18304600000000.0,"Rank":16,"Scaled Economic Indicator":63.98756944,"Log_Economic_Indicator":30.53817467},{"Country":"Switzerland","GDP Growth Weighted":58519600000000.0,"GDP Military Weighted":69.30297518,"Int. Cap Weighted":4027790000000.0,"Income Weighted":3144.063383,"Trade Weighted":5199810000000.0,"Unemployment Weighted":415.0872249,"CPI Weighted":9250.667204,"Dollar Weighted":44668700000000.0,"GDP Debt Weighted":2064.169782,"Economic Indicator":17093500000000.0,"Rank":17,"Scaled Economic Indicator":63.60331812,"Log_Economic_Indicator":30.46972209},{"Country":"Saudi Arabia","GDP Growth Weighted":57138700000000.0,"GDP Military Weighted":870.1046551,"Int. Cap Weighted":539058000000.0,"Income Weighted":3764.163346,"Trade Weighted":7359530000000.0,"Unemployment Weighted":543.6894482,"CPI Weighted":9872.685348,"Dollar Weighted":43851100000000.0,"GDP Debt Weighted":6276.053023,"Economic Indicator":16602700000000.0,"Rank":18,"Scaled Economic Indicator":63.43977169,"Log_Economic_Indicator":30.44058705},{"Country":"Indonesia","GDP Growth Weighted":72085400000000.0,"GDP Military Weighted":71.82927457,"Int. Cap Weighted":411837000000.0,"Income Weighted":3328.180186,"Trade Weighted":618203000000.0,"Unemployment Weighted":489.0078258,"CPI Weighted":10586.24818,"Dollar Weighted":8828960000000.0,"GDP Debt Weighted":3540.738253,"Economic Indicator":15403000000000.0,"Rank":19,"Scaled Economic Indicator":63.01874214,"Log_Economic_Indicator":30.3655826},{"Country":"Turkiye","GDP Growth Weighted":69656400000000.0,"GDP Military Weighted":219.7956469,"Int. Cap Weighted":272129000000.0,"Income Weighted":3527.578999,"Trade Weighted":-1911120000000.0,"Unemployment Weighted":1025.285691,"CPI Weighted":12522.86418,"Dollar Weighted":8502090000000.0,"GDP Debt Weighted":3528.846523,"Economic Indicator":14617600000000.0,"Rank":20,"Scaled Economic Indicator":62.7249637,"Log_Economic_Indicator":30.31324734},{"Country":"South Sudan","GDP Growth Weighted":69156800000000.0,"GDP Military Weighted":412.9628676,"Int. Cap Weighted":379763000000.0,"Income Weighted":3480.164638,"Trade Weighted":-62048561828.0,"Unemployment Weighted":1188.097895,"CPI Weighted":327251.4561,"Dollar Weighted":238721000000.0,"GDP Debt Weighted":5748.712137,"Economic Indicator":13887000000000.0,"Rank":21,"Scaled Economic Indicator":62.43715027,"Log_Economic_Indicator":30.26197472},{"Country":"Cote d'Ivoire","GDP Growth Weighted":3922740000000.0,"GDP Military Weighted":104.5993022,"Int. Cap Weighted":6946157014.0,"Income Weighted":4007.876883,"Trade Weighted":52676600767.0,"Unemployment Weighted":426.6423732,"CPI Weighted":9725.287311,"Dollar Weighted":126236000000000.0,"GDP Debt Weighted":4298.722956,"Economic Indicator":13414100000000.0,"Rank":22,"Scaled Economic Indicator":62.24266018,"Log_Economic_Indicator":30.22732721},{"Country":"Sweden","GDP Growth Weighted":47125900000000.0,"GDP Military Weighted":112.3309155,"Int. Cap Weighted":2083650000000.0,"Income Weighted":2691.508239,"Trade Weighted":2053450000000.0,"Unemployment Weighted":686.0143792,"CPI Weighted":9609.40935,"Dollar Weighted":4580890000000.0,"GDP Debt Weighted":4473.883442,"Economic Indicator":10297000000000.0,"Rank":23,"Scaled Economic Indicator":60.75816319,"Log_Economic_Indicator":29.96287099},{"Country":"Poland","GDP Growth Weighted":44433300000000.0,"GDP Military Weighted":182.0636604,"Int. Cap Weighted":457066000000.0,"Income Weighted":3175.386136,"Trade Weighted":264448000000.0,"Unemployment Weighted":833.8845401,"CPI Weighted":9641.752135,"Dollar Weighted":8774380000000.0,"GDP Debt Weighted":5256.914801,"Economic Indicator":9836240000000.0,"Rank":24,"Scaled Economic Indicator":60.50120465,"Log_Economic_Indicator":29.91709502},{"Country":"Belgium","GDP Growth Weighted":44806300000000.0,"GDP Military Weighted":97.20726478,"Int. Cap Weighted":3055410000000.0,"Income Weighted":2650.718892,"Trade Weighted":655287000000.0,"Unemployment Weighted":694.6510399,"CPI Weighted":9823.328841,"Dollar Weighted":2251840000000.0,"GDP Debt Weighted":9671.501964,"Economic Indicator":9557510000000.0,"Rank":25,"Scaled Economic Indicator":60.33983558,"Log_Economic_Indicator":29.88834787},{"Country":"Thailand","GDP Growth Weighted":34609100000000.0,"GDP Military Weighted":132.2158754,"Int. Cap Weighted":802050000000.0,"Income Weighted":3545.354967,"Trade Weighted":2391190000000.0,"Unemployment Weighted":88.86126079,"CPI Weighted":9694.734724,"Dollar Weighted":14500500000000.0,"GDP Debt Weighted":3328.70577,"Economic Indicator":8691190000000.0,"Rank":26,"Scaled Economic Indicator":59.80646592,"Log_Economic_Indicator":29.79333055},{"Country":"Norway","GDP Growth Weighted":37939900000000.0,"GDP Military Weighted":152.4931882,"Int. Cap Weighted":1342840000000.0,"Income Weighted":2659.843014,"Trade Weighted":3641130000000.0,"Unemployment Weighted":349.1709742,"CPI Weighted":9815.245236,"Dollar Weighted":5301120000000.0,"GDP Debt Weighted":2817.169003,"Economic Indicator":8616480000000.0,"Rank":27,"Scaled Economic Indicator":59.75800664,"Log_Economic_Indicator":29.78469776},{"Country":"Singapore","GDP Growth Weighted":25150800000000.0,"GDP Military Weighted":318.9240135,"Int. Cap Weighted":3322040000000.0,"Income Weighted":3819.049416,"Trade Weighted":6733010000000.0,"Unemployment Weighted":390.7599199,"CPI Weighted":9885.610045,"Dollar Weighted":21897800000000.0,"GDP Debt Weighted":10022.07241,"Economic Indicator":8225440000000.0,"Rank":28,"Scaled Economic Indicator":59.49729062,"Log_Economic_Indicator":29.73825241},{"Country":"Iran, Islamic Rep.","GDP Growth Weighted":36586100000000.0,"GDP Military Weighted":237.4375379,"Int. Cap Weighted":18754657133.0,"Income Weighted":3362.399633,"Trade Weighted":817054000000.0,"Unemployment Weighted":1087.521313,"CPI Weighted":22693.16472,"Dollar Weighted":2453670000000.0,"GDP Debt Weighted":7498.676724,"Economic Indicator":7646170000000.0,"Rank":29,"Scaled Economic Indicator":59.08736564,"Log_Economic_Indicator":29.66522619},{"Country":"Nigeria","GDP Growth Weighted":35477100000000.0,"GDP Military Weighted":46.61042206,"Int. Cap Weighted":77799876390.0,"Income Weighted":3333.778476,"Trade Weighted":-139536000000.0,"Unemployment Weighted":396.9705006,"CPI Weighted":13756.96678,"Dollar Weighted":3348140000000.0,"GDP Debt Weighted":6610.781664,"Economic Indicator":7424060000000.0,"Rank":30,"Scaled Economic Indicator":58.92188602,"Log_Economic_Indicator":29.63574676},{"Country":"South Africa","GDP Growth Weighted":32938000000000.0,"GDP Military Weighted":99.39422659,"Int. Cap Weighted":271983000000.0,"Income Weighted":3979.249558,"Trade Weighted":38512405094.0,"Unemployment Weighted":2092.789798,"CPI Weighted":10928.82192,"Dollar Weighted":3927560000000.0,"GDP Debt Weighted":4890.325104,"Economic Indicator":7011410000000.0,"Rank":31,"Scaled Economic Indicator":58.60087531,"Log_Economic_Indicator":29.5785602},{"Country":"Guyana","GDP Growth Weighted":343492000000.0,"GDP Military Weighted":112.9911694,"Int. Cap Weighted":67427700000000.0,"Income Weighted":4297.349886,"Trade Weighted":109491000000.0,"Unemployment Weighted":1191.727046,"CPI Weighted":9432.736903,"Dollar Weighted":52984942781.0,"GDP Debt Weighted":8087.382522,"Economic Indicator":6827710000000.0,"Rank":32,"Scaled Economic Indicator":58.45184302,"Log_Economic_Indicator":29.55201079},{"Country":"Denmark","GDP Growth Weighted":29796900000000.0,"GDP Military Weighted":122.1231783,"Int. Cap Weighted":756892000000.0,"Income Weighted":2653.712495,"Trade Weighted":1817340000000.0,"Unemployment Weighted":555.798099,"CPI Weighted":9605.643367,"Dollar Weighted":6032060000000.0,"GDP Debt Weighted":3990.209502,"Economic Indicator":6820010000000.0,"Rank":33,"Scaled Economic Indicator":58.44550813,"Log_Economic_Indicator":29.55088226},{"Country":"Malaysia","GDP Growth Weighted":25484900000000.0,"GDP Military Weighted":143.2927024,"Int. Cap Weighted":895843000000.0,"Income Weighted":3837.713155,"Trade Weighted":2797610000000.0,"Unemployment Weighted":316.9868505,"CPI Weighted":9955.624349,"Dollar Weighted":9375590000000.0,"GDP Debt Weighted":4729.301692,"Economic Indicator":6403890000000.0,"Rank":34,"Scaled Economic Indicator":58.09211423,"Log_Economic_Indicator":29.48792678},{"Country":"Israel","GDP Growth Weighted":26121900000000.0,"GDP Military Weighted":541.8216062,"Int. Cap Weighted":620661000000.0,"Income Weighted":3774.885395,"Trade Weighted":382505000000.0,"Unemployment Weighted":658.2848057,"CPI Weighted":9497.806395,"Dollar Weighted":7599080000000.0,"GDP Debt Weighted":11314.21817,"Economic Indicator":6084610000000.0,"Rank":35,"Scaled Economic Indicator":57.80502734,"Log_Economic_Indicator":29.43678359},{"Country":"Ireland","GDP Growth Weighted":26002400000000.0,"GDP Military Weighted":42.94117282,"Int. Cap Weighted":3212210000000.0,"Income Weighted":3034.178979,"Trade Weighted":4393340000000.0,"Unemployment Weighted":830.1484188,"CPI Weighted":9557.196635,"Dollar Weighted":302875000000.0,"GDP Debt Weighted":7269.18067,"Economic Indicator":5991330000000.0,"Rank":36,"Scaled Economic Indicator":57.71830701,"Log_Economic_Indicator":29.42133477},{"Country":"Ecuador","GDP Growth Weighted":7491660000000.0,"GDP Military Weighted":238.8059453,"Int. Cap Weighted":40115100000000.0,"Income Weighted":4482.669465,"Trade Weighted":73781403030.0,"Unemployment Weighted":378.010044,"CPI Weighted":9907.317241,"Dollar Weighted":299057000000.0,"GDP Debt Weighted":7344.156691,"Economic Indicator":5547120000000.0,"Rank":37,"Scaled Economic Indicator":57.28588182,"Log_Economic_Indicator":29.34430024},{"Country":"Colombia","GDP Growth Weighted":25911400000000.0,"GDP Military Weighted":310.8694826,"Int. Cap Weighted":332059000000.0,"Income Weighted":4919.597279,"Trade Weighted":-1032900000000.0,"Unemployment Weighted":1030.440241,"CPI Weighted":10260.72585,"Dollar Weighted":3401790000000.0,"GDP Debt Weighted":6496.890003,"Economic Indicator":5452380000000.0,"Rank":38,"Scaled Economic Indicator":57.18917729,"Log_Economic_Indicator":29.32707277},{"Country":"Philippines","GDP Growth Weighted":23637600000000.0,"GDP Military Weighted":114.0083032,"Int. Cap Weighted":294675000000.0,"Income Weighted":4086.791564,"Trade Weighted":-1361360000000.0,"Unemployment Weighted":302.960598,"CPI Weighted":9954.840352,"Dollar Weighted":6149980000000.0,"GDP Debt Weighted":4815.897208,"Economic Indicator":5235840000000.0,"Rank":39,"Scaled Economic Indicator":56.9617021,"Log_Economic_Indicator":29.28654913},{"Country":"Finland","GDP Growth Weighted":23257600000000.0,"GDP Military Weighted":134.3655231,"Int. Cap Weighted":653733000000.0,"Income Weighted":2621.601785,"Trade Weighted":196127000000.0,"Unemployment Weighted":784.1124024,"CPI Weighted":9771.528793,"Dollar Weighted":991006000000.0,"GDP Debt Weighted":5119.923183,"Economic Indicator":4835610000000.0,"Rank":40,"Scaled Economic Indicator":56.51532256,"Log_Economic_Indicator":29.20702869},{"Country":"Egypt","GDP Growth Weighted":22585700000000.0,"GDP Military Weighted":175.2463514,"Int. Cap Weighted":38388314513.0,"Income Weighted":3700.766057,"Trade Weighted":-1716250000000.0,"Unemployment Weighted":1001.97634,"CPI Weighted":14083.85111,"Dollar Weighted":2545080000000.0,"GDP Debt Weighted":7613.830014,"Economic Indicator":4603860000000.0,"Rank":41,"Scaled Economic Indicator":56.23963348,"Log_Economic_Indicator":29.15791597},{"Country":"Chile","GDP Growth Weighted":20881700000000.0,"GDP Military Weighted":203.8567933,"Int. Cap Weighted":743269000000.0,"Income Weighted":3945.564222,"Trade Weighted":393880000000.0,"Unemployment Weighted":773.849653,"CPI Weighted":10234.15193,"Dollar Weighted":3102300000000.0,"GDP Debt Weighted":3100.765538,"Economic Indicator":4600280000000.0,"Rank":42,"Scaled Economic Indicator":56.23526527,"Log_Economic_Indicator":29.15713779},{"Country":"Pakistan","GDP Growth Weighted":23149100000000.0,"GDP Military Weighted":321.9309683,"Int. Cap Weighted":4495094341.0,"Income Weighted":3804.410507,"Trade Weighted":-1790840000000.0,"Unemployment Weighted":221.7058686,"CPI Weighted":11427.43091,"Dollar Weighted":1364970000000.0,"GDP Debt Weighted":5414.501338,"Economic Indicator":4587690000000.0,"Rank":43,"Scaled Economic Indicator":56.21988426,"Log_Economic_Indicator":29.15439774},{"Country":"Czech Republic","GDP Growth Weighted":18796700000000.0,"GDP Military Weighted":115.5163281,"Int. Cap Weighted":388253000000.0,"Income Weighted":2487.461347,"Trade Weighted":927831000000.0,"Unemployment Weighted":500.5832514,"CPI Weighted":9693.045207,"Dollar Weighted":6937430000000.0,"GDP Debt Weighted":3751.812973,"Economic Indicator":4584690000000.0,"Rank":44,"Scaled Economic Indicator":56.21621657,"Log_Economic_Indicator":29.15374435},{"Country":"Algeria","GDP Growth Weighted":16373000000000.0,"GDP Military Weighted":450.1019159,"Int. Cap Weighted":12601943888.0,"Income Weighted":4255.613156,"Trade Weighted":199721000000.0,"Unemployment Weighted":1218.37239,"CPI Weighted":10881.74703,"Dollar Weighted":11419000000000.0,"GDP Debt Weighted":3860.907594,"Economic Indicator":4437730000000.0,"Rank":45,"Scaled Economic Indicator":56.03332997,"Log_Economic_Indicator":29.12116396},{"Country":"Greece","GDP Growth Weighted":22255800000000.0,"GDP Military Weighted":254.2555178,"Int. Cap Weighted":114217000000.0,"Income Weighted":3301.138481,"Trade Weighted":-1332480000000.0,"Unemployment Weighted":1651.082105,"CPI Weighted":9130.13348,"Dollar Weighted":643875000000.0,"GDP Debt Weighted":15955.90011,"Economic Indicator":4393720000000.0,"Rank":46,"Scaled Economic Indicator":55.97738555,"Log_Economic_Indicator":29.11119772},{"Country":"Portugal","GDP Growth Weighted":20660300000000.0,"GDP Military Weighted":133.8647104,"Int. Cap Weighted":368023000000.0,"Income Weighted":3461.291315,"Trade Weighted":-600342000000.0,"Unemployment Weighted":917.3501052,"CPI Weighted":9666.924984,"Dollar Weighted":1877680000000.0,"GDP Debt Weighted":11320.17189,"Economic Indicator":4296600000000.0,"Rank":47,"Scaled Economic Indicator":55.85191083,"Log_Economic_Indicator":29.08884498},{"Country":"Vietnam","GDP Growth Weighted":18331600000000.0,"GDP Military Weighted":204.3617936,"Int. Cap Weighted":2230050000000.0,"Income Weighted":3433.110904,"Trade Weighted":293089000000.0,"Unemployment Weighted":157.6621963,"CPI Weighted":11295.5044,"Dollar Weighted":3153250000000.0,"GDP Debt Weighted":7557.442405,"Economic Indicator":4233950000000.0,"Rank":48,"Scaled Economic Indicator":55.76946401,"Log_Economic_Indicator":29.07415747},{"Country":"Ethiopia","GDP Growth Weighted":4847420000000.0,"GDP Military Weighted":131.3630031,"Int. Cap Weighted":32185800000000.0,"Income Weighted":2983.378676,"Trade Weighted":-576706000000.0,"Unemployment Weighted":249.3541933,"CPI Weighted":16319.94597,"Dollar Weighted":229609000000.0,"GDP Debt Weighted":3284.060177,"Economic Indicator":4153360000000.0,"Rank":49,"Scaled Economic Indicator":55.66157527,"Log_Economic_Indicator":29.05493759},{"Country":"Small states","GDP Growth Weighted":17631400000000.0,"GDP Military Weighted":188.6795347,"Int. Cap Weighted":2149110000000.0,"Income Weighted":3134.317793,"Trade Weighted":20026721881.0,"Unemployment Weighted":821.8966047,"CPI Weighted":116913.64,"Dollar Weighted":82826988017.0,"GDP Debt Weighted":5994.998962,"Economic Indicator":3751470000000.0,"Rank":50,"Scaled Economic Indicator":55.09031281,"Log_Economic_Indicator":28.95316984},{"Country":"Romania","GDP Growth Weighted":16956200000000.0,"GDP Military Weighted":152.3560236,"Int. Cap Weighted":47564044086.0,"Income Weighted":3547.97207,"Trade Weighted":-795465000000.0,"Unemployment Weighted":583.2154491,"CPI Weighted":9525.371202,"Dollar Weighted":3677940000000.0,"GDP Debt Weighted":3539.837179,"Economic Indicator":3684240000000.0,"Rank":51,"Scaled Economic Indicator":54.98879458,"Log_Economic_Indicator":28.93508484},{"Country":"Iraq","GDP Growth Weighted":14928900000000.0,"GDP Military Weighted":290.6766305,"Int. Cap Weighted":20739577990.0,"Income Weighted":3070.826087,"Trade Weighted":1290640000000.0,"Unemployment Weighted":981.698553,"CPI Weighted":9390.38358,"Dollar Weighted":4604460000000.0,"GDP Debt Weighted":7728.172777,"Economic Indicator":3577370000000.0,"Rank":52,"Scaled Economic Indicator":54.8235558,"Log_Economic_Indicator":28.90564832},{"Country":"Venezuela, RB","GDP Growth Weighted":16623100000000.0,"GDP Military Weighted":126.0718243,"Int. Cap Weighted":153358000000.0,"Income Weighted":3748.871881,"Trade Weighted":200338000000.0,"Unemployment Weighted":710.1777242,"CPI Weighted":32166.7465,"Dollar Weighted":2143270000000.0,"GDP Debt Weighted":7658.375196,"Economic Indicator":3574320000000.0,"Rank":53,"Scaled Economic Indicator":54.81877499,"Log_Economic_Indicator":28.90479665},{"Country":"Peru","GDP Growth Weighted":15382800000000.0,"GDP Military Weighted":135.8803884,"Int. Cap Weighted":51646362162.0,"Income Weighted":4288.531134,"Trade Weighted":235066000000.0,"Unemployment Weighted":377.0026275,"CPI Weighted":10248.87977,"Dollar Weighted":4614400000000.0,"GDP Debt Weighted":2753.436006,"Economic Indicator":3566660000000.0,"Rank":54,"Scaled Economic Indicator":54.80673631,"Log_Economic_Indicator":28.90265201},{"Country":"Bangladesh","GDP Growth Weighted":17310700000000.0,"GDP Military Weighted":107.9736885,"Int. Cap Weighted":10807765465.0,"Income Weighted":3381.32427,"Trade Weighted":-1014270000000.0,"Unemployment Weighted":407.8766998,"CPI Weighted":11650.41412,"Dollar Weighted":1800190000000.0,"GDP Debt Weighted":4205.017468,"Economic Indicator":3541820000000.0,"Rank":55,"Scaled Economic Indicator":54.76749191,"Log_Economic_Indicator":28.8956608},{"Country":"New Zealand","GDP Growth Weighted":15571100000000.0,"GDP Military Weighted":110.6946495,"Int. Cap Weighted":4965808597.0,"Income Weighted":3190.786717,"Trade Weighted":112381000000.0,"Unemployment Weighted":486.9526221,"CPI Weighted":9654.317214,"Dollar Weighted":1407950000000.0,"GDP Debt Weighted":6813.089281,"Economic Indicator":3266760000000.0,"Rank":56,"Scaled Economic Indicator":54.31369749,"Log_Economic_Indicator":28.81481944},{"Country":"Kazakhstan","GDP Growth Weighted":14155800000000.0,"GDP Military Weighted":94.56962881,"Int. Cap Weighted":152138000000.0,"Income Weighted":2740.369519,"Trade Weighted":1473220000000.0,"Unemployment Weighted":571.4510794,"CPI Weighted":11604.81979,"Dollar Weighted":2300490000000.0,"GDP Debt Weighted":2307.554672,"Economic Indicator":3223750000000.0,"Rank":57,"Scaled Economic Indicator":54.23930615,"Log_Economic_Indicator":28.80156697},{"Country":"Qatar","GDP Growth Weighted":12792500000000.0,"GDP Military Weighted":182.8415414,"Int. Cap Weighted":362441000000.0,"Income Weighted":3616.904962,"Trade Weighted":3461110000000.0,"Unemployment Weighted":35.047653,"CPI Weighted":9583.899282,"Dollar Weighted":2359520000000.0,"GDP Debt Weighted":5209.169779,"Economic Indicator":3176810000000.0,"Rank":58,"Scaled Economic Indicator":54.15695874,"Log_Economic_Indicator":28.78689716},{"Country":"Hungary","GDP Growth Weighted":12492400000000.0,"GDP Military Weighted":110.944298,"Int. Cap Weighted":2185160000000.0,"Income Weighted":2934.551206,"Trade Weighted":469646000000.0,"Unemployment Weighted":669.2706483,"CPI Weighted":9648.875091,"Dollar Weighted":3129280000000.0,"GDP Debt Weighted":7970.244041,"Economic Indicator":3076890000000.0,"Rank":59,"Scaled Economic Indicator":53.97756636,"Log_Economic_Indicator":28.75493925},{"Country":"Kuwait","GDP Growth Weighted":11426600000000.0,"GDP Military Weighted":450.3648777,"Int. Cap Weighted":630667000000.0,"Income Weighted":3128.489141,"Trade Weighted":3256220000000.0,"Unemployment Weighted":195.6228778,"CPI Weighted":9982.583677,"Dollar Weighted":2771100000000.0,"GDP Debt Weighted":5532.990244,"Economic Indicator":2951120000000.0,"Rank":60,"Scaled Economic Indicator":53.74330053,"Log_Economic_Indicator":28.71320588},{"Country":"Ukraine","GDP Growth Weighted":12156800000000.0,"GDP Military Weighted":236.662906,"Int. Cap Weighted":33348464292.0,"Income Weighted":2513.045028,"Trade Weighted":-631600000000.0,"Unemployment Weighted":797.7449078,"CPI Weighted":13793.21394,"Dollar Weighted":1966880000000.0,"GDP Debt Weighted":3913.225165,"Economic Indicator":2568220000000.0,"Rank":61,"Scaled Economic Indicator":52.96320409,"Log_Economic_Indicator":28.57423533},{"Country":"Samoa","GDP Growth Weighted":67488483117.0,"GDP Military Weighted":180.6145521,"Int. Cap Weighted":25101100000000.0,"Income Weighted":3249.864816,"Trade Weighted":-13325433486.0,"Unemployment Weighted":715.5675787,"CPI Weighted":9467.430248,"Dollar Weighted":12056088759.0,"GDP Debt Weighted":6865.026352,"Economic Indicator":2523480000000.0,"Rank":62,"Scaled Economic Indicator":52.86454517,"Log_Economic_Indicator":28.55665971},{"Country":"Jordan","GDP Growth Weighted":2910870000000.0,"GDP Military Weighted":467.9379184,"Int. Cap Weighted":2065197796.0,"Income Weighted":3087.128453,"Trade Weighted":-648948000000.0,"Unemployment Weighted":1374.44632,"CPI Weighted":9918.823174,"Dollar Weighted":17254000000000.0,"GDP Debt Weighted":7577.894718,"Economic Indicator":2242880000000.0,"Rank":63,"Scaled Economic Indicator":52.20286168,"Log_Economic_Indicator":28.43878387},{"Country":"Lesotho","GDP Growth Weighted":196357000000.0,"GDP Military Weighted":204.4973476,"Int. Cap Weighted":20698700000000.0,"Income Weighted":3441.20858,"Trade Weighted":-121512000000.0,"Unemployment Weighted":1535.746593,"CPI Weighted":11386.97906,"Dollar Weighted":83450346536.0,"GDP Debt Weighted":3433.697466,"Economic Indicator":2105330000000.0,"Rank":64,"Scaled Economic Indicator":51.84759511,"Log_Economic_Indicator":28.37549479},{"Country":"Morocco","GDP Growth Weighted":9749070000000.0,"GDP Military Weighted":317.3562202,"Int. Cap Weighted":46565493151.0,"Income Weighted":3146.727385,"Trade Weighted":-935233000000.0,"Unemployment Weighted":922.8432061,"CPI Weighted":9604.778155,"Dollar Weighted":2079840000000.0,"GDP Debt Weighted":4128.450824,"Economic Indicator":2068930000000.0,"Rank":65,"Scaled Economic Indicator":51.74968943,"Log_Economic_Indicator":28.35805335},{"Country":"Libya","GDP Growth Weighted":5843270000000.0,"GDP Military Weighted":258.7480491,"Int. Cap Weighted":85444601613.0,"Income Weighted":3316.368683,"Trade Weighted":922784000000.0,"Unemployment Weighted":1806.081221,"CPI Weighted":13983.99762,"Dollar Weighted":7731140000000.0,"GDP Debt Weighted":4753.036445,"Economic Indicator":2042590000000.0,"Rank":66,"Scaled Economic Indicator":51.67776626,"Log_Economic_Indicator":28.34524057},{"Country":"Uzbekistan","GDP Growth Weighted":4962120000000.0,"GDP Military Weighted":281.238956,"Int. Cap Weighted":1251630000000.0,"Income Weighted":3779.845023,"Trade Weighted":-309745000000.0,"Unemployment Weighted":547.2486619,"CPI Weighted":15021.37454,"Dollar Weighted":9069650000000.0,"GDP Debt Weighted":7878.451085,"Economic Indicator":1993580000000.0,"Rank":67,"Scaled Economic Indicator":51.54142717,"Log_Economic_Indicator":28.3209524},{"Country":"Senegal","GDP Growth Weighted":1652980000000.0,"GDP Military Weighted":124.855509,"Int. Cap Weighted":6891262451.0,"Income Weighted":3793.055766,"Trade Weighted":-250376000000.0,"Unemployment Weighted":351.1968544,"CPI Weighted":9539.705511,"Dollar Weighted":15096800000000.0,"GDP Debt Weighted":8747.534675,"Economic Indicator":1815930000000.0,"Rank":68,"Scaled Economic Indicator":51.01749958,"Log_Economic_Indicator":28.22761714},{"Country":"Slovakia","GDP Growth Weighted":8379400000000.0,"GDP Military Weighted":128.2088876,"Int. Cap Weighted":106483000000.0,"Income Weighted":2495.638721,"Trade Weighted":129060000000.0,"Unemployment Weighted":1085.661917,"CPI Weighted":9633.781513,"Dollar Weighted":604746000000.0,"GDP Debt Weighted":5282.477075,"Economic Indicator":1759910000000.0,"Rank":69,"Scaled Economic Indicator":50.84160786,"Log_Economic_Indicator":28.19628285},{"Country":"Marshall Islands","GDP Growth Weighted":16989879718.0,"GDP Military Weighted":104.9360401,"Int. Cap Weighted":8361060000000.0,"Income Weighted":3833.022836,"Trade Weighted":-10161994766.0,"Unemployment Weighted":481.6950668,"CPI Weighted":10128.6205,"Dollar Weighted":9062500000000.0,"GDP Debt Weighted":5791.798071,"Economic Indicator":1744740000000.0,"Rank":70,"Scaled Economic Indicator":50.79301089,"Log_Economic_Indicator":28.18762552},{"Country":"Oman","GDP Growth Weighted":6403600000000.0,"GDP Military Weighted":759.7973168,"Int. Cap Weighted":1948700000000.0,"Income Weighted":3497.598612,"Trade Weighted":886166000000.0,"Unemployment Weighted":328.7205465,"CPI Weighted":9490.775272,"Dollar Weighted":1251560000000.0,"GDP Debt Weighted":7568.249443,"Economic Indicator":1689360000000.0,"Rank":71,"Scaled Economic Indicator":50.61196156,"Log_Economic_Indicator":28.15537243},{"Country":"Sudan","GDP Growth Weighted":3929280000000.0,"GDP Military Weighted":336.4485456,"Int. Cap Weighted":272975000000.0,"Income Weighted":3767.339052,"Trade Weighted":-151828000000.0,"Unemployment Weighted":1363.785965,"CPI Weighted":51190.07605,"Dollar Weighted":8295810000000.0,"GDP Debt Weighted":7472.996944,"Economic Indicator":1627550000000.0,"Rank":72,"Scaled Economic Indicator":50.40272791,"Log_Economic_Indicator":28.11809843},{"Country":"Luxembourg","GDP Growth Weighted":5452780000000.0,"GDP Military Weighted":43.58364155,"Int. Cap Weighted":3531900000000.0,"Income Weighted":3050.787161,"Trade Weighted":1702880000000.0,"Unemployment Weighted":494.9867422,"CPI Weighted":9759.871736,"Dollar Weighted":72121613169.0,"GDP Debt Weighted":2090.981128,"Economic Indicator":1621250000000.0,"Rank":73,"Scaled Economic Indicator":50.38093593,"Log_Economic_Indicator":28.11421629},{"Country":"Cuba","GDP Growth Weighted":6985110000000.0,"GDP Military Weighted":234.9623274,"Int. Cap Weighted":118471000000.0,"Income Weighted":3990.73499,"Trade Weighted":162830000000.0,"Unemployment Weighted":220.3698637,"CPI Weighted":9600.18699,"Dollar Weighted":370018000000.0,"GDP Debt Weighted":10651.21528,"Economic Indicator":1462150000000.0,"Rank":74,"Scaled Economic Indicator":49.80115657,"Log_Economic_Indicator":28.01093129},{"Country":"Sri Lanka","GDP Growth Weighted":6142270000000.0,"GDP Military Weighted":234.7700808,"Int. Cap Weighted":5779846048.0,"Income Weighted":3438.716507,"Trade Weighted":-204366000000.0,"Unemployment Weighted":491.0262913,"CPI Weighted":10612.72554,"Dollar Weighted":546972000000.0,"GDP Debt Weighted":6054.22385,"Economic Indicator":1263290000000.0,"Rank":75,"Scaled Economic Indicator":48.9805419,"Log_Economic_Indicator":27.86474261},{"Country":"Togo","GDP Growth Weighted":504746000000.0,"GDP Military Weighted":181.2962713,"Int. Cap Weighted":15185647916.0,"Income Weighted":3648.329977,"Trade Weighted":-57722072476.0,"Unemployment Weighted":268.3680624,"CPI Weighted":9643.627563,"Dollar Weighted":10888500000000.0,"GDP Debt Weighted":3110.653993,"Economic Indicator":1185540000000.0,"Rank":76,"Scaled Economic Indicator":48.62396515,"Log_Economic_Indicator":27.80122013},{"Country":"Croatia","GDP Growth Weighted":5185860000000.0,"GDP Military Weighted":173.0419888,"Int. Cap Weighted":20025508972.0,"Income Weighted":3284.786136,"Trade Weighted":-163435000000.0,"Unemployment Weighted":1149.726745,"CPI Weighted":9509.158645,"Dollar Weighted":1423540000000.0,"GDP Debt Weighted":6881.801635,"Economic Indicator":1165190000000.0,"Rank":77,"Scaled Economic Indicator":48.52675135,"Log_Economic_Indicator":27.78390194},{"Country":"Bulgaria","GDP Growth Weighted":4855740000000.0,"GDP Military Weighted":166.8466448,"Int. Cap Weighted":49635813916.0,"Income Weighted":3502.387087,"Trade Weighted":-99528325877.0,"Unemployment Weighted":851.8543097,"CPI Weighted":9291.467316,"Dollar Weighted":1935230000000.0,"GDP Debt Weighted":2786.459776,"Economic Indicator":1159680000000.0,"Rank":78,"Scaled Economic Indicator":48.50016474,"Log_Economic_Indicator":27.77916566},{"Country":"Dominican Republic","GDP Growth Weighted":5726690000000.0,"GDP Military Weighted":65.08257798,"Int. Cap Weighted":432062892.1000000238,"Income Weighted":4339.217892,"Trade Weighted":-363912000000.0,"Unemployment Weighted":593.4653525,"CPI Weighted":9875.802903,"Dollar Weighted":460761000000.0,"GDP Debt Weighted":3892.163174,"Economic Indicator":1155070000000.0,"Rank":79,"Scaled Economic Indicator":48.47778749,"Log_Economic_Indicator":27.77517926},{"Country":"Kenya","GDP Growth Weighted":5543210000000.0,"GDP Military Weighted":126.5874659,"Int. Cap Weighted":6266726774.0,"Income Weighted":2921.90472,"Trade Weighted":-558990000000.0,"Unemployment Weighted":306.7523382,"CPI Weighted":11837.80267,"Dollar Weighted":527335000000.0,"GDP Debt Weighted":3884.391238,"Economic Indicator":1106100000000.0,"Rank":80,"Scaled Economic Indicator":48.23464384,"Log_Economic_Indicator":27.73186435},{"Country":"Belarus","GDP Growth Weighted":5070670000000.0,"GDP Military Weighted":123.0644602,"Int. Cap Weighted":6724990787.0,"Income Weighted":2547.784527,"Trade Weighted":-94864241567.0,"Unemployment Weighted":610.6363287,"CPI Weighted":25620.29503,"Dollar Weighted":501150000000.0,"GDP Debt Weighted":2699.121059,"Economic Indicator":1055440000000.0,"Rank":81,"Scaled Economic Indicator":47.97143526,"Log_Economic_Indicator":27.68497497},{"Country":"Djibouti","GDP Growth Weighted":173483000000.0,"GDP Military Weighted":172.9324885,"Int. Cap Weighted":5694380000000.0,"Income Weighted":3077.900656,"Trade Weighted":3983650000000.0,"Unemployment Weighted":2489.61228,"CPI Weighted":9793.138471,"Dollar Weighted":31078956877.0,"GDP Debt Weighted":4445.665472,"Economic Indicator":1005610000000.0,"Rank":82,"Scaled Economic Indicator":47.6999613,"Log_Economic_Indicator":27.63661314},{"Country":"Uruguay","GDP Growth Weighted":4409030000000.0,"GDP Military Weighted":179.752856,"Int. Cap Weighted":103157000000.0,"Income Weighted":3950.939432,"Trade Weighted":65974881875.0,"Unemployment Weighted":820.8734868,"CPI Weighted":12262.02444,"Dollar Weighted":1056410000000.0,"GDP Debt Weighted":4909.887718,"Economic Indicator":1004360000000.0,"Rank":83,"Scaled Economic Indicator":47.69298874,"Log_Economic_Indicator":27.63537102},{"Country":"Myanmar","GDP Growth Weighted":4742780000000.0,"GDP Military Weighted":256.0292355,"Int. Cap Weighted":46021285175.0,"Income Weighted":3187.358973,"Trade Weighted":26918714488.0,"Unemployment Weighted":76.69187245,"CPI Weighted":9965.906469,"Dollar Weighted":465202000000.0,"GDP Debt Weighted":8495.667073,"Economic Indicator":1002370000000.0,"Rank":84,"Scaled Economic Indicator":47.68185809,"Log_Economic_Indicator":27.63338814},{"Country":"Guatemala","GDP Growth Weighted":4893450000000.0,"GDP Military Weighted":43.76427242,"Int. Cap Weighted":5132929598.0,"Income Weighted":3987.421183,"Trade Weighted":-533659000000.0,"Unemployment Weighted":261.7420746,"CPI Weighted":10344.95946,"Dollar Weighted":760011000000.0,"GDP Debt Weighted":7807.255603,"Economic Indicator":1001840000000.0,"Rank":85,"Scaled Economic Indicator":47.67888469,"Log_Economic_Indicator":27.63285844},{"Country":"Yemen, Rep.","GDP Growth Weighted":4639430000000.0,"GDP Military Weighted":309.2192716,"Int. Cap Weighted":-3091125179.0,"Income Weighted":3471.455051,"Trade Weighted":-232763000000.0,"Unemployment Weighted":1396.62356,"CPI Weighted":10438.20301,"Dollar Weighted":380418000000.0,"GDP Debt Weighted":5548.558853,"Economic Indicator":942341000000.0,"Rank":86,"Scaled Economic Indicator":47.33520491,"Log_Economic_Indicator":27.57163349},{"Country":"Slovenia","GDP Growth Weighted":4370780000000.0,"GDP Military Weighted":113.1132857,"Int. Cap Weighted":49470036643.0,"Income Weighted":2400.991657,"Trade Weighted":199703000000.0,"Unemployment Weighted":650.2803923,"CPI Weighted":9452.979456,"Dollar Weighted":191141000000.0,"GDP Debt Weighted":6320.330098,"Economic Indicator":918188000000.0,"Rank":87,"Scaled Economic Indicator":47.18944883,"Log_Economic_Indicator":27.54566773},{"Country":"Costa Rica","GDP Growth Weighted":4228810000000.0,"GDP Military Weighted":114.4565107,"Int. Cap Weighted":35904886171.0,"Income Weighted":4591.747231,"Trade Weighted":-33004007871.0,"Unemployment Weighted":789.5740342,"CPI Weighted":9701.230187,"Dollar Weighted":542848000000.0,"GDP Debt Weighted":8868.696351,"Economic Indicator":900336000000.0,"Rank":88,"Scaled Economic Indicator":47.07923924,"Log_Economic_Indicator":27.5260344},{"Country":"Chad","GDP Growth Weighted":933498000000.0,"GDP Military Weighted":307.4045792,"Int. Cap Weighted":6970990000000.0,"Income Weighted":3498.779979,"Trade Weighted":-50241175310.0,"Unemployment Weighted":92.04049925,"CPI Weighted":9907.679228,"Dollar Weighted":52259182740.0,"GDP Debt Weighted":3883.35419,"Economic Indicator":884000000000.0,"Rank":89,"Scaled Economic Indicator":46.97644912,"Log_Economic_Indicator":27.50772282},{"Country":"Serbia","GDP Growth Weighted":3995420000000.0,"GDP Military Weighted":205.6193907,"Int. Cap Weighted":52888438267.0,"Income Weighted":3710.586543,"Trade Weighted":-447446000000.0,"Unemployment Weighted":1567.010533,"CPI Weighted":10414.04924,"Dollar Weighted":1091290000000.0,"GDP Debt Weighted":5502.425312,"Economic Indicator":868757000000.0,"Rank":90,"Scaled Economic Indicator":46.87881398,"Log_Economic_Indicator":27.49032957},{"Country":"Lithuania","GDP Growth Weighted":4001570000000.0,"GDP Military Weighted":120.5750827,"Int. Cap Weighted":80209746938.0,"Income Weighted":3350.7407,"Trade Weighted":-8399772696.0,"Unemployment Weighted":943.5781491,"CPI Weighted":9613.982523,"Dollar Weighted":517579000000.0,"GDP Debt Weighted":3693.479234,"Economic Indicator":859253000000.0,"Rank":91,"Scaled Economic Indicator":46.8170618,"Log_Economic_Indicator":27.47932871},{"Country":"Tanzania","GDP Growth Weighted":3807850000000.0,"GDP Military Weighted":93.32633072,"Int. Cap Weighted":72792377286.0,"Income Weighted":3371.662277,"Trade Weighted":-201371000000.0,"Unemployment Weighted":258.3528044,"CPI Weighted":12220.12896,"Dollar Weighted":1099990000000.0,"GDP Debt Weighted":3594.648123,"Economic Indicator":858712000000.0,"Rank":92,"Scaled Economic Indicator":46.81352838,"Log_Economic_Indicator":27.47869925},{"Country":"Ghana","GDP Growth Weighted":4108970000000.0,"GDP Military Weighted":33.75063011,"Int. Cap Weighted":13473567252.0,"Income Weighted":3603.210413,"Trade Weighted":-310439000000.0,"Unemployment Weighted":447.5559396,"CPI Weighted":14336.03893,"Dollar Weighted":463132000000.0,"GDP Debt Weighted":5227.655133,"Economic Indicator":838411000000.0,"Rank":93,"Scaled Economic Indicator":46.67922949,"Log_Economic_Indicator":27.45477453},{"Country":"Tunisia","GDP Growth Weighted":3949540000000.0,"GDP Military Weighted":166.7795289,"Int. Cap Weighted":3993619818.0,"Income Weighted":3509.691965,"Trade Weighted":-311548000000.0,"Unemployment Weighted":1429.639125,"CPI Weighted":10844.63994,"Dollar Weighted":680568000000.0,"GDP Debt Weighted":3794.32757,"Economic Indicator":827210000000.0,"Rank":94,"Scaled Economic Indicator":46.60372794,"Log_Economic_Indicator":27.44132428},{"Country":"Panama","GDP Growth Weighted":3964160000000.0,"GDP Military Weighted":223.5076568,"Int. Cap Weighted":22695308130.0,"Income Weighted":4812.076523,"Trade Weighted":-148422000000.0,"Unemployment Weighted":546.7966922,"CPI Weighted":10083.67582,"Dollar Weighted":285086000000.0,"GDP Debt Weighted":4083.968672,"Economic Indicator":808768000000.0,"Rank":95,"Scaled Economic Indicator":46.47716597,"Log_Economic_Indicator":27.41877785},{"Country":"Turkmenistan","GDP Growth Weighted":2779970000000.0,"GDP Military Weighted":113.9696524,"Int. Cap Weighted":2288330000000.0,"Income Weighted":3421.161915,"Trade Weighted":9751487266.0,"Unemployment Weighted":474.3113609,"CPI Weighted":10321.80502,"Dollar Weighted":59911847130.0,"GDP Debt Weighted":4050.262597,"Economic Indicator":791792000000.0,"Rank":96,"Scaled Economic Indicator":46.35809077,"Log_Economic_Indicator":27.39756516},{"Country":"Syrian Arab Republic","GDP Growth Weighted":2814670000000.0,"GDP Military Weighted":271.186004,"Int. Cap Weighted":1358360000000.0,"Income Weighted":3368.627395,"Trade Weighted":-291210000000.0,"Unemployment Weighted":1130.029683,"CPI Weighted":10014.57714,"Dollar Weighted":471416000000.0,"GDP Debt Weighted":4874.106165,"Economic Indicator":716791000000.0,"Rank":97,"Scaled Economic Indicator":45.79947392,"Log_Economic_Indicator":27.29805017},{"Country":"Cyprus","GDP Growth Weighted":2149600000000.0,"GDP Military Weighted":170.2658235,"Int. Cap Weighted":2201240000000.0,"Income Weighted":3089.216628,"Trade Weighted":-33555061640.0,"Unemployment Weighted":850.7223673,"CPI Weighted":9271.628483,"Dollar Weighted":163571000000.0,"GDP Debt Weighted":13324.99368,"Economic Indicator":663046000000.0,"Rank":98,"Scaled Economic Indicator":45.36196519,"Log_Economic_Indicator":27.22011003},{"Country":"Paraguay","GDP Growth Weighted":2799140000000.0,"GDP Military Weighted":86.81481055,"Int. Cap Weighted":9814257815.0,"Income Weighted":4642.376193,"Trade Weighted":102241000000.0,"Unemployment Weighted":517.3851347,"CPI Weighted":10381.94998,"Dollar Weighted":490463000000.0,"GDP Debt Weighted":10627.08766,"Economic Indicator":620081000000.0,"Rank":99,"Scaled Economic Indicator":44.98589688,"Log_Economic_Indicator":27.15311521},{"Country":"Bahrain","GDP Growth Weighted":2653810000000.0,"GDP Military Weighted":373.727549,"Int. Cap Weighted":40073562827.0,"Income Weighted":3277.714763,"Trade Weighted":372414000000.0,"Unemployment Weighted":112.3446626,"CPI Weighted":9787.56067,"Dollar Weighted":346709000000.0,"GDP Debt Weighted":4857.909762,"Economic Indicator":606682000000.0,"Rank":100,"Scaled Economic Indicator":44.8632724,"Log_Economic_Indicator":27.13127023},{"Country":"Cameroon","GDP Growth Weighted":2872230000000.0,"GDP Military Weighted":110.0422994,"Int. Cap Weighted":2449842373.0,"Income Weighted":4207.721948,"Trade Weighted":-74961399853.0,"Unemployment Weighted":378.0979593,"CPI Weighted":9849.636315,"Dollar Weighted":272507000000.0,"GDP Debt Weighted":4882.903461,"Economic Indicator":594446000000.0,"Rank":101,"Scaled Economic Indicator":44.74890398,"Log_Economic_Indicator":27.11089603},{"Country":"Bolivia","GDP Growth Weighted":2483320000000.0,"GDP Military Weighted":160.6219761,"Int. Cap Weighted":51530007094.0,"Income Weighted":4455.476045,"Trade Weighted":-29832523076.0,"Unemployment Weighted":298.141525,"CPI Weighted":10822.26324,"Dollar Weighted":816400000000.0,"GDP Debt Weighted":6313.586062,"Economic Indicator":580473000000.0,"Rank":102,"Scaled Economic Indicator":44.61538137,"Log_Economic_Indicator":27.0871096},{"Country":"Congo, Dem. Rep.","GDP Growth Weighted":2848740000000.0,"GDP Military Weighted":92.33067099,"Int. Cap Weighted":17532901348.0,"Income Weighted":4399.219675,"Trade Weighted":-134706000000.0,"Unemployment Weighted":394.4665811,"CPI Weighted":9781.549536,"Dollar Weighted":81505864611.0,"GDP Debt Weighted":5452.144181,"Economic Indicator":566181000000.0,"Rank":103,"Scaled Economic Indicator":44.4754414,"Log_Economic_Indicator":27.06217994},{"Country":"Latvia","GDP Growth Weighted":2577840000000.0,"GDP Military Weighted":134.3461749,"Int. Cap Weighted":20064350061.0,"Income Weighted":3317.51736,"Trade Weighted":-115565000000.0,"Unemployment Weighted":1038.382482,"CPI Weighted":9399.387946,"Dollar Weighted":450062000000.0,"GDP Debt Weighted":5283.831531,"Economic Indicator":551025000000.0,"Rank":104,"Scaled Economic Indicator":44.32312319,"Log_Economic_Indicator":27.03504516},{"Country":"Uganda","GDP Growth Weighted":2376120000000.0,"GDP Military Weighted":147.1586882,"Int. Cap Weighted":13649749349.0,"Income Weighted":3175.98932,"Trade Weighted":-200833000000.0,"Unemployment Weighted":294.4555611,"CPI Weighted":11843.29334,"Dollar Weighted":787759000000.0,"GDP Debt Weighted":3627.548923,"Economic Indicator":535282000000.0,"Rank":105,"Scaled Economic Indicator":44.16041768,"Log_Economic_Indicator":27.00605993},{"Country":"Nepal","GDP Growth Weighted":1958320000000.0,"GDP Military Weighted":133.4743469,"Int. Cap Weighted":896880000000.0,"Income Weighted":2883.236593,"Trade Weighted":-509619000000.0,"Unemployment Weighted":1019.276022,"CPI Weighted":12014.38073,"Dollar Weighted":522779000000.0,"GDP Debt Weighted":4165.065499,"Economic Indicator":482668000000.0,"Rank":106,"Scaled Economic Indicator":43.57963232,"Log_Economic_Indicator":26.90259573},{"Country":"Trinidad and Tobago","GDP Growth Weighted":2131540000000.0,"GDP Military Weighted":66.9521235,"Int. Cap Weighted":34070791630.0,"Income Weighted":3494.013379,"Trade Weighted":-237683000000.0,"Unemployment Weighted":439.3962499,"CPI Weighted":10434.93793,"Dollar Weighted":747384000000.0,"GDP Debt Weighted":4056.679103,"Economic Indicator":480685000000.0,"Rank":107,"Scaled Economic Indicator":43.55651219,"Log_Economic_Indicator":26.89847699},{"Country":"Estonia","GDP Growth Weighted":2155150000000.0,"GDP Military Weighted":174.9087134,"Int. Cap Weighted":63721528656.0,"Income Weighted":3067.461805,"Trade Weighted":33362999678.0,"Unemployment Weighted":783.8137945,"CPI Weighted":9772.012112,"Dollar Weighted":127937000000.0,"GDP Debt Weighted":1082.827712,"Economic Indicator":453532000000.0,"Rank":108,"Scaled Economic Indicator":43.23011476,"Log_Economic_Indicator":26.8403308},{"Country":"Benin","GDP Growth Weighted":1023540000000.0,"GDP Military Weighted":72.76579424,"Int. Cap Weighted":-1347097440.0,"Income Weighted":3119.483283,"Trade Weighted":-49837269432.0,"Unemployment Weighted":142.825566,"CPI Weighted":9611.643165,"Dollar Weighted":2101290000000.0,"GDP Debt Weighted":7765.795772,"Economic Indicator":409719000000.0,"Rank":109,"Scaled Economic Indicator":42.65983009,"Log_Economic_Indicator":26.73873725},{"Country":"Burkina Faso","GDP Growth Weighted":1089030000000.0,"GDP Military Weighted":133.2223395,"Int. Cap Weighted":1286473945.0,"Income Weighted":3305.264202,"Trade Weighted":-69906941518.0,"Unemployment Weighted":382.3244605,"CPI Weighted":9567.125791,"Dollar Weighted":1950740000000.0,"GDP Debt Weighted":5860.089581,"Economic Indicator":406018000000.0,"Rank":110,"Scaled Economic Indicator":42.60889318,"Log_Economic_Indicator":26.72966307},{"Country":"Zambia","GDP Growth Weighted":1848540000000.0,"GDP Military Weighted":149.2520911,"Int. Cap Weighted":16319485167.0,"Income Weighted":4080.295519,"Trade Weighted":21150751282.0,"Unemployment Weighted":881.631667,"CPI Weighted":12111.14451,"Dollar Weighted":169741000000.0,"GDP Debt Weighted":4815.666409,"Economic Indicator":390430000000.0,"Rank":111,"Scaled Economic Indicator":42.38913174,"Log_Economic_Indicator":26.6905136},{"Country":"Tuvalu","GDP Growth Weighted":3471560226.0,"GDP Military Weighted":156.5609888,"Int. Cap Weighted":133064000000.0,"Income Weighted":3465.483468,"Trade Weighted":-1056250000000.0,"Unemployment Weighted":641.8192477,"CPI Weighted":12323.71128,"Dollar Weighted":4801040000000.0,"GDP Debt Weighted":3561.747323,"Economic Indicator":388480000000.0,"Rank":112,"Scaled Economic Indicator":42.36103193,"Log_Economic_Indicator":26.68550775},{"Country":"Gabon","GDP Growth Weighted":1341180000000.0,"GDP Military Weighted":157.3800339,"Int. Cap Weighted":134529000000.0,"Income Weighted":3226.451259,"Trade Weighted":350087000000.0,"Unemployment Weighted":1844.722082,"CPI Weighted":9866.639141,"Dollar Weighted":701113000000.0,"GDP Debt Weighted":8210.19359,"Economic Indicator":386808000000.0,"Rank":113,"Scaled Economic Indicator":42.33681702,"Log_Economic_Indicator":26.68119397},{"Country":"Niger","GDP Growth Weighted":847978000000.0,"GDP Military Weighted":126.403664,"Int. Cap Weighted":723270256.2999999523,"Income Weighted":3474.710595,"Trade Weighted":-122438000000.0,"Unemployment Weighted":107.6488902,"CPI Weighted":9518.860918,"Dollar Weighted":2280020000000.0,"GDP Debt Weighted":6980.509866,"Economic Indicator":385426000000.0,"Rank":114,"Scaled Economic Indicator":42.31672322,"Log_Economic_Indicator":26.67761435},{"Country":"El Salvador","GDP Growth Weighted":1964010000000.0,"GDP Military Weighted":100.1199612,"Int. Cap Weighted":5729195139.0,"Income Weighted":4010.705745,"Trade Weighted":-367716000000.0,"Unemployment Weighted":474.5297004,"CPI Weighted":9563.8137,"Dollar Weighted":271068000000.0,"GDP Debt Weighted":5304.841811,"Economic Indicator":383711000000.0,"Rank":115,"Scaled Economic Indicator":42.2916904,"Log_Economic_Indicator":26.67315487},{"Country":"Papua New Guinea","GDP Growth Weighted":1621160000000.0,"GDP Military Weighted":39.21828575,"Int. Cap Weighted":25193885155.0,"Income Weighted":3498.879948,"Trade Weighted":172287000000.0,"Unemployment Weighted":235.5496338,"CPI Weighted":10748.24434,"Dollar Weighted":208262000000.0,"GDP Debt Weighted":3985.261437,"Economic Indicator":364806000000.0,"Rank":116,"Scaled Economic Indicator":42.00807819,"Log_Economic_Indicator":26.62263068},{"Country":"Cambodia","GDP Growth Weighted":1459370000000.0,"GDP Military Weighted":160.0603904,"Int. Cap Weighted":5346833505.0,"Income Weighted":2857.57177,"Trade Weighted":-52755110307.0,"Unemployment Weighted":53.58008478,"CPI Weighted":9917.710633,"Dollar Weighted":703814000000.0,"GDP Debt Weighted":5874.413376,"Economic Indicator":357514000000.0,"Rank":117,"Scaled Economic Indicator":41.89474137,"Log_Economic_Indicator":26.60244025},{"Country":"Honduras","GDP Growth Weighted":1677630000000.0,"GDP Military Weighted":124.0497517,"Int. Cap Weighted":12283857358.0,"Income Weighted":4772.054029,"Trade Weighted":-312151000000.0,"Unemployment Weighted":506.4924938,"CPI Weighted":10571.53238,"Dollar Weighted":333762000000.0,"GDP Debt Weighted":7554.623808,"Economic Indicator":338915000000.0,"Rank":118,"Scaled Economic Indicator":41.5948394,"Log_Economic_Indicator":26.54901411},{"Country":"Haiti","GDP Growth Weighted":1175780000000.0,"GDP Military Weighted":76.00316306,"Int. Cap Weighted":1102250000000.0,"Income Weighted":3161.990669,"Trade Weighted":-239784000000.0,"Unemployment Weighted":1332.080448,"CPI Weighted":11909.64813,"Dollar Weighted":155536000000.0,"GDP Debt Weighted":7426.022838,"Economic Indicator":336957000000.0,"Rank":119,"Scaled Economic Indicator":41.5623131,"Log_Economic_Indicator":26.54321971},{"Country":"Palau","GDP Growth Weighted":21947201184.0,"GDP Military Weighted":76.61329446,"Int. Cap Weighted":159870000000.0,"Income Weighted":3792.835756,"Trade Weighted":-18131917038.0,"Unemployment Weighted":269.2551159,"CPI Weighted":9875.241727,"Dollar Weighted":3179120000000.0,"GDP Debt Weighted":4745.258921,"Economic Indicator":336476000000.0,"Rank":120,"Scaled Economic Indicator":41.55429556,"Log_Economic_Indicator":26.54179142},{"Country":"Vanuatu","GDP Growth Weighted":65506846689.0,"GDP Military Weighted":211.1421062,"Int. Cap Weighted":3162010000000.0,"Income Weighted":3353.998855,"Trade Weighted":-6547803238.0,"Unemployment Weighted":537.586883,"CPI Weighted":9591.705684,"Dollar Weighted":22955954170.0,"GDP Debt Weighted":7523.798141,"Economic Indicator":330943000000.0,"Rank":121,"Scaled Economic Indicator":41.46122428,"Log_Economic_Indicator":26.5252112},{"Country":"Bosnia and Herzegovina","GDP Growth Weighted":1570130000000.0,"GDP Military Weighted":116.6044851,"Int. Cap Weighted":4099599064.0,"Income Weighted":2828.370115,"Trade Weighted":-336360000000.0,"Unemployment Weighted":2322.087654,"CPI Weighted":17318.17116,"Dollar Weighted":463529000000.0,"GDP Debt Weighted":3510.263039,"Economic Indicator":327153000000.0,"Rank":122,"Scaled Economic Indicator":41.39657163,"Log_Economic_Indicator":26.51369363},{"Country":"Botswana","GDP Growth Weighted":1239390000000.0,"GDP Military Weighted":277.5453268,"Int. Cap Weighted":4298681373.0,"Income Weighted":3969.535834,"Trade Weighted":-28994174560.0,"Unemployment Weighted":1782.020946,"CPI Weighted":10577.3932,"Dollar Weighted":687238000000.0,"GDP Debt Weighted":2120.425945,"Economic Indicator":314132000000.0,"Rank":123,"Scaled Economic Indicator":41.1685947,"Log_Economic_Indicator":26.47308061},{"Country":"Equatorial Guinea","GDP Growth Weighted":1296840000000.0,"GDP Military Weighted":158.92358,"Int. Cap Weighted":51834919855.0,"Income Weighted":3398.154186,"Trade Weighted":232998000000.0,"Unemployment Weighted":775.0486507,"CPI Weighted":9865.581049,"Dollar Weighted":172236000000.0,"GDP Debt Weighted":14167.85928,"Economic Indicator":305075000000.0,"Rank":124,"Scaled Economic Indicator":41.00435926,"Log_Economic_Indicator":26.44382283},{"Country":"Central African Republic","GDP Growth Weighted":179841000000.0,"GDP Military Weighted":164.2486356,"Int. Cap Weighted":2687790000000.0,"Income Weighted":3614.553756,"Trade Weighted":-25684802241.0,"Unemployment Weighted":540.3870971,"CPI Weighted":11002.02806,"Dollar Weighted":21721026295.0,"GDP Debt Weighted":3505.971215,"Economic Indicator":304351000000.0,"Rank":125,"Scaled Economic Indicator":40.99102434,"Log_Economic_Indicator":26.44144727},{"Country":"Brunei","GDP Growth Weighted":1234920000000.0,"GDP Military Weighted":277.3919617,"Int. Cap Weighted":7198489357.0,"Income Weighted":4424.274311,"Trade Weighted":326831000000.0,"Unemployment Weighted":659.8188279,"CPI Weighted":9305.964282,"Dollar Weighted":239503000000.0,"GDP Debt Weighted":8230.528934,"Economic Indicator":304337000000.0,"Rank":126,"Scaled Economic Indicator":40.99077513,"Log_Economic_Indicator":26.44140288},{"Country":"Kosovo","GDP Growth Weighted":651166000000.0,"GDP Military Weighted":143.3066856,"Int. Cap Weighted":1767660000000.0,"Income Weighted":3146.464183,"Trade Weighted":-155164000000.0,"Unemployment Weighted":1056.095569,"CPI Weighted":9766.490711,"Dollar Weighted":73803425816.0,"GDP Debt Weighted":6206.792603,"Economic Indicator":298864000000.0,"Rank":127,"Scaled Economic Indicator":40.88889403,"Log_Economic_Indicator":26.42325324},{"Country":"Zimbabwe","GDP Growth Weighted":1484340000000.0,"GDP Military Weighted":157.3935709,"Int. Cap Weighted":2966086987.0,"Income Weighted":4140.569217,"Trade Weighted":-162504000000.0,"Unemployment Weighted":542.5009986,"CPI Weighted":27142.51169,"Dollar Weighted":31929729574.0,"GDP Debt Weighted":4815.666409,"Economic Indicator":284108000000.0,"Rank":128,"Scaled Economic Indicator":40.60466737,"Log_Economic_Indicator":26.37261958},{"Country":"Jamaica","GDP Growth Weighted":1272910000000.0,"GDP Military Weighted":91.84745542,"Int. Cap Weighted":7602524805.0,"Income Weighted":3239.908837,"Trade Weighted":-24222855485.0,"Unemployment Weighted":696.2251022,"CPI Weighted":10780.74906,"Dollar Weighted":244985000000.0,"GDP Debt Weighted":11620.35329,"Economic Indicator":277418000000.0,"Rank":129,"Scaled Economic Indicator":40.47091883,"Log_Economic_Indicator":26.3487929},{"Country":"Nicaragua","GDP Growth Weighted":972684000000.0,"GDP Military Weighted":59.95122866,"Int. Cap Weighted":768853000000.0,"Income Weighted":3184.354266,"Trade Weighted":-156633000000.0,"Unemployment Weighted":530.0058099,"CPI Weighted":10945.68471,"Dollar Weighted":177915000000.0,"GDP Debt Weighted":6241.053462,"Economic Indicator":273550000000.0,"Rank":130,"Scaled Economic Indicator":40.39209922,"Log_Economic_Indicator":26.33475155},{"Country":"Georgia","GDP Growth Weighted":1285590000000.0,"GDP Military Weighted":286.6243814,"Int. Cap Weighted":80145569348.0,"Income Weighted":3538.047121,"Trade Weighted":-205789000000.0,"Unemployment Weighted":1477.751811,"CPI Weighted":9854.585292,"Dollar Weighted":222173000000.0,"GDP Debt Weighted":3439.614304,"Economic Indicator":266771000000.0,"Rank":131,"Scaled Economic Indicator":40.25123717,"Log_Economic_Indicator":26.30965764},{"Country":"Republic of the Congo","GDP Growth Weighted":1133790000000.0,"GDP Military Weighted":235.5047585,"Int. Cap Weighted":27827084345.0,"Income Weighted":4644.268085,"Trade Weighted":79870098350.0,"Unemployment Weighted":1904.952562,"CPI Weighted":10031.35689,"Dollar Weighted":229510000000.0,"GDP Debt Weighted":5962.806505,"Economic Indicator":260479000000.0,"Rank":132,"Scaled Economic Indicator":40.11725454,"Log_Economic_Indicator":26.28578925},{"Country":"Rwanda","GDP Growth Weighted":660891000000.0,"GDP Military Weighted":136.595744,"Int. Cap Weighted":1238030000000.0,"Income Weighted":3757.811936,"Trade Weighted":-101585000000.0,"Unemployment Weighted":1099.561974,"CPI Weighted":10610.39229,"Dollar Weighted":82778780825.0,"GDP Debt Weighted":3238.849698,"Economic Indicator":254100000000.0,"Rank":133,"Scaled Economic Indicator":39.97807098,"Log_Economic_Indicator":26.26099435},{"Country":"Micronesia","GDP Growth Weighted":29544603949.0,"GDP Military Weighted":165.7191973,"Int. Cap Weighted":2436890000000.0,"Income Weighted":3200.230781,"Trade Weighted":-14766262331.0,"Unemployment Weighted":1519.716453,"CPI Weighted":9655.201201,"Dollar Weighted":14930810515.0,"GDP Debt Weighted":3510.473609,"Economic Indicator":249614000000.0,"Rank":134,"Scaled Economic Indicator":39.87808743,"Log_Economic_Indicator":26.24318275},{"Country":"Mauritius","GDP Growth Weighted":1028760000000.0,"GDP Military Weighted":15.22673815,"Int. Cap Weighted":7592741088.0,"Income Weighted":3718.767336,"Trade Weighted":-72787462424.0,"Unemployment Weighted":714.2590307,"CPI Weighted":10060.55304,"Dollar Weighted":360229000000.0,"GDP Debt Weighted":4817.321572,"Economic Indicator":235256000000.0,"Rank":135,"Scaled Economic Indicator":39.54552909,"Log_Economic_Indicator":26.18393903},{"Country":"Mozambique","GDP Growth Weighted":1245860000000.0,"GDP Military Weighted":99.38160773,"Int. Cap Weighted":9101517943.0,"Income Weighted":3830.89975,"Trade Weighted":-389285000000.0,"Unemployment Weighted":313.6037297,"CPI Weighted":11330.57951,"Dollar Weighted":237720000000.0,"GDP Debt Weighted":6604.906495,"Economic Indicator":234926000000.0,"Rank":136,"Scaled Economic Indicator":39.53765483,"Log_Economic_Indicator":26.18253626},{"Country":"Mali","GDP Growth Weighted":1143740000000.0,"GDP Military Weighted":182.7051436,"Int. Cap Weighted":1901514496.0,"Income Weighted":3288.189124,"Trade Weighted":-127769000000.0,"Unemployment Weighted":153.7577883,"CPI Weighted":9585.184615,"Dollar Weighted":173322000000.0,"GDP Debt Weighted":8153.293393,"Economic Indicator":233494000000.0,"Rank":137,"Scaled Economic Indicator":39.50334557,"Log_Economic_Indicator":26.17642423},{"Country":"Tajikistan","GDP Growth Weighted":589773000000.0,"GDP Military Weighted":103.3020771,"Int. Cap Weighted":1051390000000.0,"Income Weighted":3425.270508,"Trade Weighted":-200521000000.0,"Unemployment Weighted":902.2706665,"CPI Weighted":10009.53104,"Dollar Weighted":72870187332.0,"GDP Debt Weighted":3710.918301,"Economic Indicator":210329000000.0,"Rank":138,"Scaled Economic Indicator":38.91682436,"Log_Economic_Indicator":26.07193821},{"Country":"Bahamas","GDP Growth Weighted":1012120000000.0,"GDP Military Weighted":245.1660171,"Int. Cap Weighted":34818997366.0,"Income Weighted":3053.042439,"Trade Weighted":-62647965514.0,"Unemployment Weighted":1101.115642,"CPI Weighted":9726.594227,"Dollar Weighted":97043746433.0,"GDP Debt Weighted":4065.493704,"Economic Indicator":209346000000.0,"Rank":139,"Scaled Economic Indicator":38.89054185,"Log_Economic_Indicator":26.0672561},{"Country":"Madagascar","GDP Growth Weighted":1017080000000.0,"GDP Military Weighted":67.6906726,"Int. Cap Weighted":23389485054.0,"Income Weighted":3245.179462,"Trade Weighted":-83197039389.0,"Unemployment Weighted":254.2072223,"CPI Weighted":11359.60153,"Dollar Weighted":101459000000.0,"GDP Debt Weighted":3053.748376,"Economic Indicator":207581000000.0,"Rank":140,"Scaled Economic Indicator":38.84301182,"Log_Economic_Indicator":26.05878885},{"Country":"Laos","GDP Growth Weighted":1034560000000.0,"GDP Military Weighted":141.839513,"Int. Cap Weighted":22843753716.0,"Income Weighted":3224.663056,"Trade Weighted":-113510000000.0,"Unemployment Weighted":180.5645394,"CPI Weighted":10292.50132,"Dollar Weighted":93354085234.0,"GDP Debt Weighted":5282.717915,"Economic Indicator":207181000000.0,"Rank":141,"Scaled Economic Indicator":38.83217872,"Log_Economic_Indicator":26.05685898},{"Country":"Namibia","GDP Growth Weighted":992351000000.0,"GDP Military Weighted":318.1634067,"Int. Cap Weighted":2002647304.0,"Income Weighted":3823.126437,"Trade Weighted":-146957000000.0,"Unemployment Weighted":1959.658514,"CPI Weighted":10922.13313,"Dollar Weighted":143768000000.0,"GDP Debt Weighted":7719.966269,"Economic Indicator":198352000000.0,"Rank":142,"Scaled Economic Indicator":38.58770545,"Log_Economic_Indicator":26.01330721},{"Country":"Malta","GDP Growth Weighted":995521000000.0,"GDP Military Weighted":53.28069731,"Int. Cap Weighted":-214156000000.0,"Income Weighted":2972.045432,"Trade Weighted":90221362197.0,"Unemployment Weighted":529.4927347,"CPI Weighted":9661.723511,"Dollar Weighted":106699000000.0,"GDP Debt Weighted":8940.4585,"Economic Indicator":197381000000.0,"Rank":143,"Scaled Economic Indicator":38.56015948,"Log_Economic_Indicator":26.00840002},{"Country":"North Macedonia","GDP Growth Weighted":925259000000.0,"GDP Military Weighted":136.1169881,"Int. Cap Weighted":6512790032.0,"Income Weighted":3546.799693,"Trade Weighted":-154651000000.0,"Unemployment Weighted":2656.92809,"CPI Weighted":9753.464993,"Dollar Weighted":239945000000.0,"GDP Debt Weighted":7366.128286,"Economic Indicator":194232000000.0,"Rank":144,"Scaled Economic Indicator":38.46990402,"Log_Economic_Indicator":25.99232143},{"Country":"Mongolia","GDP Growth Weighted":865826000000.0,"GDP Military Weighted":86.51454027,"Int. Cap Weighted":9471195750.0,"Income Weighted":3459.813469,"Trade Weighted":-66998985505.0,"Unemployment Weighted":568.7841399,"CPI Weighted":12027.78197,"Dollar Weighted":201151000000.0,"GDP Debt Weighted":7161.292793,"Economic Indicator":187528000000.0,"Rank":145,"Scaled Economic Indicator":38.27270591,"Log_Economic_Indicator":25.95719151},{"Country":"Maldives","GDP Growth Weighted":305641000000.0,"GDP Military Weighted":276.663984,"Int. Cap Weighted":1668360000000.0,"Income Weighted":3462.405243,"Trade Weighted":-522876000000.0,"Unemployment Weighted":678.6966777,"CPI Weighted":10660.51364,"Dollar Weighted":42552259435.0,"GDP Debt Weighted":3481.520137,"Economic Indicator":179932000000.0,"Rank":146,"Scaled Economic Indicator":38.04061671,"Log_Economic_Indicator":25.9158459},{"Country":"Guinea","GDP Growth Weighted":793101000000.0,"GDP Military Weighted":149.1578356,"Int. Cap Weighted":345128960.6999999881,"Income Weighted":3509.3306,"Trade Weighted":-153504000000.0,"Unemployment Weighted":471.9643064,"CPI Weighted":14287.63456,"Dollar Weighted":67467365643.0,"GDP Debt Weighted":8803.736793,"Economic Indicator":150051000000.0,"Rank":147,"Scaled Economic Indicator":37.02119811,"Log_Economic_Indicator":25.73424122},{"Country":"Moldova","GDP Growth Weighted":717468000000.0,"GDP Military Weighted":34.28452197,"Int. Cap Weighted":1648270192.0,"Income Weighted":2912.986843,"Trade Weighted":-214071000000.0,"Unemployment Weighted":257.8875544,"CPI Weighted":10943.34087,"Dollar Weighted":191864000000.0,"GDP Debt Weighted":2625.976614,"Economic Indicator":141438000000.0,"Rank":148,"Scaled Economic Indicator":36.68936166,"Log_Economic_Indicator":25.6751261},{"Country":"Somalia","GDP Growth Weighted":552442000000.0,"GDP Military Weighted":170.4529142,"Int. Cap Weighted":37168690558.0,"Income Weighted":3810.626277,"Trade Weighted":-403784000000.0,"Unemployment Weighted":1776.640086,"CPI Weighted":10056.70358,"Dollar Weighted":567133000000.0,"GDP Debt Weighted":5379.281899,"Economic Indicator":130540000000.0,"Rank":149,"Scaled Economic Indicator":36.23928787,"Log_Economic_Indicator":25.59494756},{"Country":"Mauritania","GDP Growth Weighted":552381000000.0,"GDP Military Weighted":204.1515979,"Int. Cap Weighted":-2932847495.0,"Income Weighted":3614.314421,"Trade Weighted":-53527271993.0,"Unemployment Weighted":949.8844636,"CPI Weighted":10155.75827,"Dollar Weighted":60485934523.0,"GDP Debt Weighted":5711.114033,"Economic Indicator":110879000000.0,"Rank":150,"Scaled Economic Indicator":35.32293131,"Log_Economic_Indicator":25.4317029},{"Country":"Kyrgyzstan","GDP Growth Weighted":565970000000.0,"GDP Military Weighted":148.796529,"Int. Cap Weighted":3308490214.0,"Income Weighted":2793.095132,"Trade Weighted":-193494000000.0,"Unemployment Weighted":296.9904069,"CPI Weighted":11024.9154,"Dollar Weighted":162360000000.0,"GDP Debt Weighted":5461.227804,"Economic Indicator":110412000000.0,"Rank":151,"Scaled Economic Indicator":35.29922848,"Log_Economic_Indicator":25.42748035},{"Country":"Montenegro","GDP Growth Weighted":516492000000.0,"GDP Military Weighted":162.0866762,"Int. Cap Weighted":16024701437.0,"Income Weighted":3537.572927,"Trade Weighted":-99686580931.0,"Unemployment Weighted":1876.183767,"CPI Weighted":9307.448874,"Dollar Weighted":75735101566.0,"GDP Debt Weighted":7606.08422,"Economic Indicator":102506000000.0,"Rank":152,"Scaled Economic Indicator":34.88217745,"Log_Economic_Indicator":25.35318466},{"Country":"Barbados","GDP Growth Weighted":430255000000.0,"GDP Military Weighted":206.5359582,"Int. Cap Weighted":8722984307.0,"Income Weighted":4683.716547,"Trade Weighted":-24136502890.0,"Unemployment Weighted":922.2707252,"CPI Weighted":10169.22043,"Dollar Weighted":65455629360.0,"GDP Debt Weighted":9160.805336,"Economic Indicator":91055122137.0,"Rank":153,"Scaled Economic Indicator":34.21724984,"Log_Economic_Indicator":25.2347309},{"Country":"Suriname","GDP Growth Weighted":345862000000.0,"GDP Military Weighted":148.36577,"Int. Cap Weighted":27144201257.0,"Income Weighted":2728.516546,"Trade Weighted":102102000000.0,"Unemployment Weighted":777.3257265,"CPI Weighted":14461.97652,"Dollar Weighted":49620412375.0,"GDP Debt Weighted":5519.98437,"Economic Indicator":87059127342.0,"Rank":154,"Scaled Economic Indicator":33.96533448,"Log_Economic_Indicator":25.18985335},{"Country":"Fiji","GDP Growth Weighted":381969000000.0,"GDP Military Weighted":139.8229826,"Int. Cap Weighted":-273615907.8999999762,"Income Weighted":2916.537521,"Trade Weighted":-32451753469.0,"Unemployment Weighted":410.8327326,"CPI Weighted":10164.33596,"Dollar Weighted":73725220331.0,"GDP Debt Weighted":6704.319004,"Economic Indicator":80493831059.0,"Rank":155,"Scaled Economic Indicator":33.52520529,"Log_Economic_Indicator":25.11144639},{"Country":"Eswatini","GDP Growth Weighted":370095000000.0,"GDP Military Weighted":179.7448832,"Int. Cap Weighted":368558080.3000000119,"Income Weighted":3111.02241,"Trade Weighted":-12018344951.0,"Unemployment Weighted":2485.485266,"CPI Weighted":10831.12141,"Dollar Weighted":54489678992.0,"GDP Debt Weighted":3291.302411,"Economic Indicator":78302977815.0,"Rank":156,"Scaled Economic Indicator":33.37030416,"Log_Economic_Indicator":25.08385147},{"Country":"Timor-Leste","GDP Growth Weighted":114422000000.0,"GDP Military Weighted":226.2621745,"Int. Cap Weighted":536061000000.0,"Income Weighted":3413.424834,"Trade Weighted":-75893818561.0,"Unemployment Weighted":347.2600773,"CPI Weighted":10946.35298,"Dollar Weighted":41196866204.0,"GDP Debt Weighted":4501.348971,"Economic Indicator":73020733841.0,"Rank":157,"Scaled Economic Indicator":32.97825233,"Log_Economic_Indicator":25.01400926},{"Country":"Sierra Leone","GDP Growth Weighted":309565000000.0,"GDP Military Weighted":98.9046727,"Int. Cap Weighted":5434661291.0,"Income Weighted":3877.051181,"Trade Weighted":-69307760872.0,"Unemployment Weighted":383.3463995,"CPI Weighted":12602.825,"Dollar Weighted":40070275731.0,"GDP Debt Weighted":4377.333676,"Economic Indicator":59532707319.0,"Rank":158,"Scaled Economic Indicator":31.83189869,"Log_Economic_Indicator":24.8097917},{"Country":"Liberia","GDP Growth Weighted":234739000000.0,"GDP Military Weighted":109.7572535,"Int. Cap Weighted":24092821910.0,"Income Weighted":3286.008915,"Trade Weighted":-22295101053.0,"Unemployment Weighted":243.3713108,"CPI Weighted":12478.72195,"Dollar Weighted":34402259248.0,"GDP Debt Weighted":4828.310172,"Economic Indicator":50567757376.0,"Rank":159,"Scaled Economic Indicator":30.91572712,"Log_Economic_Indicator":24.64658},{"Country":"Bhutan","GDP Growth Weighted":172994000000.0,"GDP Military Weighted":277.4686443,"Int. Cap Weighted":5748585365.0,"Income Weighted":4164.832074,"Trade Weighted":-34117658681.0,"Unemployment Weighted":285.3487907,"CPI Weighted":11720.3841,"Dollar Weighted":88385714504.0,"GDP Debt Weighted":7300.252531,"Economic Indicator":40600378066.0,"Rank":160,"Scaled Economic Indicator":29.68338063,"Log_Economic_Indicator":24.42704322},{"Country":"Belize","GDP Growth Weighted":180424000000.0,"GDP Military Weighted":87.67712936,"Int. Cap Weighted":133141810.099999994,"Income Weighted":3201.967542,"Trade Weighted":2690054625.0,"Unemployment Weighted":816.2063304,"CPI Weighted":9549.083527,"Dollar Weighted":25413728645.0,"GDP Debt Weighted":5328.626164,"Economic Indicator":38908547275.0,"Rank":161,"Scaled Economic Indicator":29.44445533,"Log_Economic_Indicator":24.38447979},{"Country":"Kiribati","GDP Growth Weighted":16805912522.0,"GDP Military Weighted":185.6942391,"Int. Cap Weighted":22389305.6400000006,"Income Weighted":2922.048408,"Trade Weighted":-11922016566.0,"Unemployment Weighted":142.7818079,"CPI Weighted":8906.574568,"Dollar Weighted":363302000000.0,"GDP Debt Weighted":6287.598948,"Economic Indicator":38501427246.0,"Rank":162,"Scaled Economic Indicator":29.38541007,"Log_Economic_Indicator":24.37396115},{"Country":"Comoros","GDP Growth Weighted":90602314105.0,"GDP Military Weighted":182.5365425,"Int. Cap Weighted":166565000000.0,"Income Weighted":4759.918906,"Trade Weighted":-17079872020.0,"Unemployment Weighted":460.2939124,"CPI Weighted":9904.753425,"Dollar Weighted":15491714100.0,"GDP Debt Weighted":7287.492119,"Economic Indicator":34618145958.0,"Rank":163,"Scaled Economic Indicator":28.78860907,"Log_Economic_Indicator":24.26764383},{"Country":"Cabo Verde","GDP Growth Weighted":165123000000.0,"GDP Military Weighted":54.2036024,"Int. Cap Weighted":1070537257.0,"Income Weighted":4641.256973,"Trade Weighted":-31090379558.0,"Unemployment Weighted":1169.727722,"CPI Weighted":9576.176461,"Dollar Weighted":41887975098.0,"GDP Debt Weighted":8078.094235,"Economic Indicator":34211503727.0,"Rank":164,"Scaled Economic Indicator":28.72228098,"Log_Economic_Indicator":24.25582779},{"Country":"Guinea-Bissau","GDP Growth Weighted":102713000000.0,"GDP Military Weighted":147.4247883,"Int. Cap Weighted":749293456.8999999762,"Income Weighted":3495.16989,"Trade Weighted":-11414442005.0,"Unemployment Weighted":305.8451399,"CPI Weighted":9640.993537,"Dollar Weighted":94564389469.0,"GDP Debt Weighted":12379.81845,"Economic Indicator":28932590994.0,"Rank":165,"Scaled Economic Indicator":27.78151388,"Log_Economic_Indicator":24.08823451},{"Country":"Gambia","GDP Growth Weighted":130652000000.0,"GDP Military Weighted":82.10666272,"Int. Cap Weighted":91029498.4699999988,"Income Weighted":3504.203915,"Trade Weighted":-18017595771.0,"Unemployment Weighted":762.7489846,"CPI Weighted":11210.45128,"Dollar Weighted":16893132568.0,"GDP Debt Weighted":10591.77762,"Economic Indicator":26026985350.0,"Rank":166,"Scaled Economic Indicator":27.18742157,"Log_Economic_Indicator":23.98239973},{"Country":"Seychelles","GDP Growth Weighted":119285000000.0,"GDP Military Weighted":127.9726927,"Int. Cap Weighted":2254029857.0,"Income Weighted":3306.163104,"Trade Weighted":-13584133489.0,"Unemployment Weighted":1581.848211,"CPI Weighted":9555.12896,"Dollar Weighted":32496501200.0,"GDP Debt Weighted":5369.482152,"Economic Indicator":25973612597.0,"Rank":167,"Scaled Economic Indicator":27.17589853,"Log_Economic_Indicator":23.98034696},{"Country":"Solomon Islands","GDP Growth Weighted":105391000000.0,"GDP Military Weighted":208.9143431,"Int. Cap Weighted":10521518095.0,"Income Weighted":3845.043066,"Trade Weighted":-9055959603.0,"Unemployment Weighted":118.0032853,"CPI Weighted":10098.6295,"Dollar Weighted":36303368386.0,"GDP Debt Weighted":3449.825541,"Economic Indicator":24855019810.0,"Rank":168,"Scaled Economic Indicator":26.92878914,"Log_Economic_Indicator":23.93632557},{"Country":"Sao Tome and Principe","GDP Growth Weighted":24188568289.0,"GDP Military Weighted":168.5226524,"Int. Cap Weighted":25092052485.0,"Income Weighted":2961.394371,"Trade Weighted":61064363735.0,"Unemployment Weighted":1375.341104,"CPI Weighted":11744.7319,"Dollar Weighted":4880036688.0,"GDP Debt Weighted":5757.491666,"Economic Indicator":13941361006.0,"Rank":169,"Scaled Economic Indicator":23.68312639,"Log_Economic_Indicator":23.35812587},{"Country":"Tonga","GDP Growth Weighted":37184896062.0,"GDP Military Weighted":266.3568879,"Int. Cap Weighted":567697457.2000000477,"Income Weighted":3446.983179,"Trade Weighted":-16086958619.0,"Unemployment Weighted":202.1424111,"CPI Weighted":9742.807076,"Dollar Weighted":13484827251.0,"GDP Debt Weighted":4724.833129,"Economic Indicator":7233537690.0,"Rank":170,"Scaled Economic Indicator":20.0,"Log_Economic_Indicator":22.70199406}]